smb_sync/__init__.py
smb_sync/__main__.py
smb_sync/cli.py
smb_sync/file_base.py
smb_sync/file_factory.py
smb_sync/file_local.py
smb_sync/file_samba.py
smb_sync-0.0.6.dist-info/METADATA
smb_sync-0.0.6.dist-info/WHEEL
smb_sync-0.0.6.dist-info/entry_points.txt
smb_sync-0.0.6.dist-info/RECORD
